odoo/addons/hr_contract_bonus/README.rst
odoo/addons/hr_contract_bonus/__init__.py
odoo/addons/hr_contract_bonus/__manifest__.py
odoo/addons/hr_contract_bonus/i18n/es.po
odoo/addons/hr_contract_bonus/i18n/hr_contract_bonus.pot
odoo/addons/hr_contract_bonus/i18n/it.po
odoo/addons/hr_contract_bonus/models/__init__.py
odoo/addons/hr_contract_bonus/models/hr_contract.py
odoo/addons/hr_contract_bonus/models/hr_contract_bonus.py
odoo/addons/hr_contract_bonus/readme/CONTRIBUTORS.md
odoo/addons/hr_contract_bonus/readme/DESCRIPTION.md
odoo/addons/hr_contract_bonus/readme/USAGE.md
odoo/addons/hr_contract_bonus/security/ir.model.access.csv
odoo/addons/hr_contract_bonus/static/description/icon.png
odoo/addons/hr_contract_bonus/static/description/icon.svg
odoo/addons/hr_contract_bonus/static/description/index.html
odoo/addons/hr_contract_bonus/tests/__init__.py
odoo/addons/hr_contract_bonus/tests/test_hr_contract_bonus.py
odoo/addons/hr_contract_bonus/views/hr_contract_bonus_views.xml
odoo/addons/hr_contract_bonus/views/hr_contract_views.xml
odoo_addon_hr_contract_bonus-17.0.1.0.0.3.dist-info/METADATA
odoo_addon_hr_contract_bonus-17.0.1.0.0.3.dist-info/WHEEL
odoo_addon_hr_contract_bonus-17.0.1.0.0.3.dist-info/top_level.txt
odoo_addon_hr_contract_bonus-17.0.1.0.0.3.dist-info/RECORD
